{

    "welcome": [
        {
            "src": "https://adapter.codelab.club/video/1593410656522462.mp4",
            "title": ""
        }

    ],
    "首页": [
        {
            "src": "https://adapter.codelab.club/video/1593410656522462.mp4",
            "title": "video"
        },
        {
            "src": "https://adapter.codelab.club/video/1593410656522462.mp4",
            "title": "video"
        },
        {
            "src": "https://adapter.codelab.club/video/1593410656522462.mp4",
            "title": "video"
        },
        {
            "src": "https://adapter.codelab.club/video/1593410656522462.mp4",
            "title": "video"
        }
    ],
    "来自CodeLab": [

        {
            "src": "https://adapter.codelab.club/video/1540219015667808.mp4 ",
            "title": "巴甫洛夫的机器人",
            "num":"3"
        },

        {
            "src": "https://adapter.codelab.club/video/1576905320614182.mp4",
            "title": "闪现",
            "num":"5"
        },
        {
            "src": "https://adapter.codelab.club/video/1576905372587643.mp4",
            "title": "Seeing Spaces",
            "num":"6"
        },
        {
            "src": "https://adapter.codelab.club/video/1576905337206766.mp4",
            "title": "魔杖升窗",
            "num":"7"
        },
        {
            "src": "https://adapter.codelab.club/video/1583984194594670.mp4 ",
            "title": "读书与思考",
            "num":"8"
        },
        
        {
            "src": "https://adapter.codelab.club/video/1587801240738968.mp4",
            "title": "积木消失了",
            "num":"12"
        },
        {
            "src": "https://adapter.codelab.club/video/1588665494072465.mp4",
            "title": "我的世界Minecraft",
            "num":"13"
        },
        {
            "src": "https://adapter.codelab.club/video/1588741044537372.mp4",
            "title": "Sonic Pi",
            "num":"14"
        },
        {
            "src": "https://adapter.codelab.club/video/AR.mp4 ",
            "title": "鼻梁上的老花镜（增强现实）",
            "num":"15"
        },
        {
            "src": "https://adapter.codelab.club/video/adapter_google_teachable_machine.mp4",
            "title": "Teachable Machine",
            "num":"18"
        },
        {
            "src": "https://adapter.codelab.club/video/arduino.mp4",
            "title": "接入arduino",
            "num":"19"
        },
        {
            "src": "https://adapter.codelab.club/video/blender.mp4 ",
            "title": "接入blender（连接游戏、电影和VR）",
            "num":"21"
        },
        {
            "src": "https://adapter.codelab.club/video/blockly_cozmo.mp4 ",
            "title": "Cozmo接入在线课程平台",
            "num":"22"
        },
        {
            "src": "https://adapter.codelab.club/video/body_programming.mp4",
            "title": "Body Programming",
            "num":"23"
        },
        {
            "src": "https://adapter.codelab.club/video/candy_vector.mp4 ",
            "title": "Candy Language for Vector",
            "num":"24"
        },
        {
            "src": "https://adapter.codelab.club/video/codelab_ipad.mp4",
            "title": "空间魔方开关",
            "num":"25"
        },
        {
            "src": "https://adapter.codelab.club/video/codelab有嘻哈.mp4 ",
            "title": "CodeLab有嘻哈",
            "num":"26"
        },
        {
            "src": "https://adapter.codelab.club/video/cosplayhi渡边君.mp4 ",
            "title": "渡边君",
            "num":"27"
        },
        {
            "src": "https://adapter.codelab.club/video/cube symphony.mp4 ",
            "title": "魔方交响乐",
            "num":"28"
        },
        {
            "src": "https://adapter.codelab.club/video/dlib_face.mp4 ",
            "title": "人脸地标（Python程序接入Scratch）",
            "num":"29"
        },
        {
            "src": "https://adapter.codelab.club/video/hi渡边君.mp4",
            "title": "Hi 渡边君",
            "num":"35"
        },
        {
            "src": "https://adapter.codelab.club/video/dynamicland_01.mp4 ",
            "title": "拧动棱镜1",
            "num":"30"
        },
        {
            "src": "https://adapter.codelab.club/video/dynamicland_02.mp4",
            "title": "拧动棱镜2",
            "num":"31"
        },
        {
            "src": "https://adapter.codelab.club/video/jupyter_scratch.mp4",
            "title": "Jupyter + Scratch",
            "num":"37"
        },
        {
            "src": "https://adapter.codelab.club/video/leju_codelab.mp4 ",
            "title": "CodeLab X Leju Robot",
            "num":"38"
        },
        {
            "src": "https://adapter.codelab.club/video/magic-eye-tracker.mp4 ",
            "title": "霍格沃兹模式1",
            "num":"39"
        },
        {
            "src": "https://adapter.codelab.club/video/magic_joy_con.mp4",
            "title": "霍格沃兹模式2",
            "num":"40"
        },
        {
            "src": "https://adapter.codelab.club/video/python_neverland.mp4",
            "title": "I am reading！",
            "num":"43"
        },
        {
            "src": "https://adapter.codelab.club/video/scratch-smart-home.mp4",
            "title": "运动检测开关灯",
            "num":"44"
        },
        {
            "src": "https://adapter.codelab.club/video/scratch_rainrow.mp4",
            "title": "彩虹的旋律",
            "num":"45"
        },
        {
            "src": "https://adapter.codelab.club/video/tm_scratch_dy.mp4 ",
            "title": "CodeLab Adapter ❤ Teachable Machine",
            "num":"51"
        },
        {
            "src": "https://adapter.codelab.club/video/toio_candy.mp4",
            "title": "谁动了我的糖果",
            "num":"53"
        },
        {
            "src": "https://adapter.codelab.club/video/toio_music.mp4",
            "title": "Toio Music Interface1",
            "num":"55"
        },
        {
            "src": "https://adapter.codelab.club/video/toio_music2.mp4",
            "title": "Toio Music Interface2",
            "num":"56"
        },
        {
            "src": "https://adapter.codelab.club/video/turnofflight_byfinger.mp4 ",
            "title": "收工，吃饭",
            "num":"59"
        },
        {
            "src": "https://adapter.codelab.club/video/unity.mp4 ",
            "title": "Unity X Lego X Scratch 3 Adapter（by 联想研究院）",
            "num":"60"
        },
        {
            "src": "https://adapter.codelab.club/video/wechat.mp4",
            "title": "做一个微信聊天界面",
            "num":"65"
        },
        {
            "src": "https://adapter.codelab.club/video/wechat_extension.mp4",
            "title": "微信插件",
            "num":"66"
        },
        {
            "src": "https://adapter.codelab.club/video/where-did-the-human-go.mp4 ",
            "title": "Cozmo vs Vector: Where did the human go?",
            "num":"68"
        },
        {
            "src": "https://adapter.codelab.club/video/一场烟火.mp4",
            "title": "一场烟火",
            "num":"69"
        },
        {
            "src": "https://adapter.codelab.club/video/两只老虎.mp4",
            "title": "击掌奏乐",
            "num":"70"
        },
        {
            "src": "https://adapter.codelab.club/video/二进制.mp4",
            "title": "二进制",
            "num":"71"
        },
        {
            "src": "https://adapter.codelab.club/video/击灭那盏灯.mp4",
            "title": "击灭那盏灯2",
            "num":"72"
        },
        {
            "src": "https://adapter.codelab.club/video/命运之手.mp4",
            "title": "命运之手",
            "num":"73"
        },
        {
            "src": "https://adapter.codelab.club/video/姿势乐谱.mp4",
            "title": "姿势乐谱",
            "num":"74"
        },
        {
            "src": "https://adapter.codelab.club/video/学会使用变量.mp4 ",
            "title": "体验者初次学会使用变量",
            "num":"76"
        },
        {
            "src": "https://adapter.codelab.club/video/小房间与大房间.mp4",
            "title": "小房间与大房间",
            "num":"88"
        },
        {
            "src": "https://adapter.codelab.club/video/山寨版龟派气功.mp4",
            "title": "山寨版龟派气功",
            "num":"89"
        },
        {
            "src": "https://adapter.codelab.club/video/手势窗帘.mp4",
            "title": "手势窗帘",
            "num":"90"
        },
        {
            "src": "https://adapter.codelab.club/video/掌控板.mp4",
            "title": "掌控版",
            "num":"92"
        },
        {
            "src": "https://adapter.codelab.club/video/智能音箱.mp4",
            "title": "智能音箱",
            "num":"93"
        },
        {
            "src": "https://adapter.codelab.club/video/模拟器.mp4",
            "title": "模拟器（by 联想研究院）",
            "num":"94"
        },
        {
            "src": "https://adapter.codelab.club/video/灵光一现.mp4 ",
            "title": "灵光一现",
            "num":"95"
        },
        {
            "src": "https://adapter.codelab.club/video/眼动仪.mp4 ",
            "title": "眼动仪",
            "num":"96"
        },
        {
            "src": "https://adapter.codelab.club/video/自制门禁.mp4",
            "title": "自制门禁",
            "num":"97"
        },
        {
            "src": "https://adapter.codelab.club/video/蜡笔调色盘.mp4",
            "title": "蜡笔调色盘",
            "num":"98"
        },
        {
            "src": "https://adapter.codelab.club/video/重力效应.mp4 ",
            "title": "重力效应",
            "num":"100"
        },
        {
            "src": "https://adapter.codelab.club/video/闭眼请熄灯.mp4",
            "title": "闭眼请熄灯",
            "num":"101"
        }
        
    ],
    "来自社区": [
        
        {
            "src": "https://adapter.codelab.club/video/toio-etoys.mp4",
            "title": "Toio etoys",
            "num":"52"
        },
        {
            "src": "https://adapter.codelab.club/video/toio_fly.mp4 ",
            "title": "天空没有留下鸟的痕迹，但Toio已飞过",
            "num":"54"
        },
        {
            "src": "https://adapter.codelab.club/video/toio_neverland_logo_light.mp4",
            "title": "在你转身之后，岁月无光",
            "num":"57"
        },
        {
            "src": "https://adapter.codelab.club/video/toio泡泡龙.mp4",
            "title": "Toio泡泡龙",
            "num":"58"
        },
        {
            "src": "https://adapter.codelab.club/video/vector_labo.mp4 ",
            "title": "Switch Labo ♥ Vector",
            "num":"61"
        },
        {
            "src": "https://adapter.codelab.club/video/vector_leapmotion.mp4",
            "title": "Oh my vector",
            "num":"62"
        },
        {
            "src": "https://adapter.codelab.club/video/wand.mp4",
            "title": "霍格沃兹模式3",
            "num":"63"
        },
        {
            "src": "https://adapter.codelab.club/video/wand_tello.mp4",
            "title": "灰袍巫师",
            "num":"64"
        },
        {
            "src": "https://adapter.codelab.club/video/wechat_iot.mp4 ",
            "title": "Scratch X 微信 X IoT",
            "num":"67"
        },
        {
            "src": "https://adapter.codelab.club/video/拍案惊球.mp4",
            "title": "拍案惊球",
            "num":"91"
        },
        {
            "src": "https://adapter.codelab.club/video/要有光.mp4",
            "title": "要有光",
            "num":"99"
        },
        {
            "src": "https://adapter.codelab.club/video/eye_light.mp4",
            "title": "目之所及",
            "num":"32"
        },
        {
            "src": "https://adapter.codelab.club/video/fly.mp4 ",
            "title": "四轴飞行器",
            "num":"33"
        },
        {
            "src": "https://adapter.codelab.club/video/game_adapter.mp4",
            "title": "接入3D游戏",
            "num":"34"
        },
        {
            "src": "https://adapter.codelab.club/video/1572097577962892.mp4",
            "title": "可穿戴设备&魔杖",
            "num":"4"
        },
        {
            "src": "https://adapter.codelab.club/video/1587120578222179.mp4",
            "title": "RoboMaster EP & Lego",
            "num":"10"
        },
        {
            "src": "https://adapter.codelab.club/video/1587801214121847.mp4",
            "title": "video",
            "num":"11"
        },
        {
            "src": "https://adapter.codelab.club/video/Magic classroom.mp4",
            "title": "魔法教室",
            "num":"16"
        },
        {
            "src": "https://adapter.codelab.club/video/Rotating-the-earth .mp4 ",
            "title": "给我一个toio，我可以转动地球",
            "num":"17"
        },
        {
            "src": "https://adapter.codelab.club/video/hungry_robot.mp4",
            "title": "Hungry Robot",
            "num":"36"
        },
        {
            "src": "https://adapter.codelab.club/video/microbitble_magic.mp4 ",
            "title": "Incendio（火焰咒）",
            "num":"41"
        },
        {
            "src": "https://adapter.codelab.club/video/physics_leapmotion.mp4",
            "title": "Physics Extension + Leap Motion",
            "num":"42"
        },
        {
            "src": "https://adapter.codelab.club/video/supermarry.mp4",
            "title": "超级玛丽 & Leap Motion",
            "num":"46"
        },
        {
            "src": "https://adapter.codelab.club/video/switch_light.mp4 ",
            "title": "击灭那盏灯1",
            "num":"47"
        },
        {
            "src": "https://adapter.codelab.club/video/tello_joy_con.mp4",
            "title": "DJI Tello X Switch Joy-Con",
            "num":"48"
        },
        {
            "src": "https://adapter.codelab.club/video/tello_labo.mp4 ",
            "title": "DJI Tello X Switch Labo",
            "num":"49"
        },
        {
            "src": "https://adapter.codelab.club/video/tello_leapmotion.mp4",
            "title": "DJI Tello X Leap Motion",
            "num":"50"
        },
        {
            "src": "https://adapter.codelab.club/video/1537510098140.mp4",
            "title": "控制优必选Alpha机器人",
            "num":"1"
            
        },
        {
            "src": "https://adapter.codelab.club/video/1539392124109888.mp4",
            "title": "冲啊，先驱音速",
            "num":"2"
        }


    ]
}